{
  "openapi": "3.0.0",
  "paths": {
    "/api/auth/register": {
      "post": {
        "operationId": "AuthController_register",
        "summary": "用户注册",
        "parameters": [],
        "requestBody": {
          "required": true,
          "description": "注册信息",
          "content": {
            "application/json": {
              "schema": {
                "$ref": "#/components/schemas/RegisterDto"
              }
            }
          }
        },
        "responses": {
          "200": {
            "description": "成功注册用户",
            "content": {
              "application/json": {
                "schema": {
                  "type": "object",
                  "properties": {
                    "code": {
                      "type": "number",
                      "example": 0
                    },
                    "message": {
                      "type": "string",
                      "example": "成功"
                    },
                    "data": {
                      "$ref": "#/components/schemas/AuthResponseDto"
                    }
                  }
                }
              }
            }
          }
        },
        "tags": [
          "认证"
        ]
      }
    },
    "/api/auth/login": {
      "post": {
        "operationId": "AuthController_login",
        "summary": "用户登录",
        "parameters": [],
        "requestBody": {
          "required": true,
          "description": "登录信息",
          "content": {
            "application/json": {
              "schema": {
                "$ref": "#/components/schemas/LoginDto"
              }
            }
          }
        },
        "responses": {
          "200": {
            "description": "成功登录",
            "content": {
              "application/json": {
                "schema": {
                  "type": "object",
                  "properties": {
                    "code": {
                      "type": "number",
                      "example": 0
                    },
                    "message": {
                      "type": "string",
                      "example": "成功"
                    },
                    "data": {
                      "$ref": "#/components/schemas/AuthResponseDto"
                    }
                  }
                }
              }
            }
          }
        },
        "tags": [
          "认证"
        ]
      }
    },
    "/api/auth/wechat-login": {
      "post": {
        "operationId": "AuthController_wechatLogin",
        "summary": "微信小程序登录",
        "parameters": [],
        "requestBody": {
          "required": true,
          "description": "微信登录凭证",
          "content": {
            "application/json": {
              "schema": {
                "$ref": "#/components/schemas/WechatLoginDto"
              }
            }
          }
        },
        "responses": {
          "200": {
            "description": "成功微信登录",
            "content": {
              "application/json": {
                "schema": {
                  "type": "object",
                  "properties": {
                    "code": {
                      "type": "number",
                      "example": 0
                    },
                    "message": {
                      "type": "string",
                      "example": "成功"
                    },
                    "data": {
                      "$ref": "#/components/schemas/AuthResponseDto"
                    }
                  }
                }
              }
            }
          }
        },
        "tags": [
          "认证"
        ]
      }
    },
    "/api/users": {
      "post": {
        "operationId": "UserController_create",
        "summary": "创建用户",
        "parameters": [],
        "requestBody": {
          "required": true,
          "description": "用户信息",
          "content": {
            "application/json": {
              "schema": {
                "$ref": "#/components/schemas/CreateUserDto"
              }
            }
          }
        },
        "responses": {
          "201": {
            "description": "成功创建用户",
            "content": {
              "application/json": {
                "schema": {
                  "type": "object",
                  "properties": {
                    "code": {
                      "type": "number",
                      "example": 0
                    },
                    "message": {
                      "type": "string",
                      "example": "成功"
                    },
                    "data": {
                      "$ref": "#/components/schemas/User"
                    }
                  }
                }
              }
            }
          }
        },
        "tags": [
          "用户管理"
        ],
        "security": [
          {
            "bearer": []
          }
        ]
      },
      "get": {
        "operationId": "UserController_findAll",
        "summary": "获取用户列表",
        "parameters": [],
        "responses": {
          "200": {
            "description": "成功获取用户列表",
            "content": {
              "application/json": {
                "schema": {
                  "type": "object",
                  "properties": {
                    "items": {
                      "type": "array",
                      "items": {
                        "$ref": "#/components/schemas/User"
                      }
                    },
                    "page": {
                      "type": "number",
                      "example": 1
                    },
                    "limit": {
                      "type": "number",
                      "example": 10
                    },
                    "total": {
                      "type": "number",
                      "example": 100
                    },
                    "totalPages": {
                      "type": "number",
                      "example": 10
                    }
                  }
                }
              }
            }
          }
        },
        "tags": [
          "用户管理"
        ],
        "security": [
          {
            "bearer": []
          }
        ]
      }
    },
    "/api/users/profile": {
      "get": {
        "operationId": "UserController_getProfile",
        "summary": "获取当前用户信息",
        "parameters": [],
        "responses": {
          "200": {
            "description": "成功获取用户信息",
            "content": {
              "application/json": {
                "schema": {
                  "type": "object",
                  "properties": {
                    "code": {
                      "type": "number",
                      "example": 0
                    },
                    "message": {
                      "type": "string",
                      "example": "成功"
                    },
                    "data": {
                      "$ref": "#/components/schemas/User"
                    }
                  }
                }
              }
            }
          }
        },
        "tags": [
          "用户管理"
        ],
        "security": [
          {
            "bearer": []
          }
        ]
      }
    },
    "/api/users/{id}": {
      "get": {
        "operationId": "UserController_findOne",
        "summary": "获取用户详情",
        "parameters": [
          {
            "name": "id",
            "required": true,
            "in": "path",
            "schema": {
              "type": "string"
            }
          }
        ],
        "responses": {
          "200": {
            "description": "成功获取用户详情",
            "content": {
              "application/json": {
                "schema": {
                  "type": "object",
                  "properties": {
                    "code": {
                      "type": "number",
                      "example": 0
                    },
                    "message": {
                      "type": "string",
                      "example": "成功"
                    },
                    "data": {
                      "$ref": "#/components/schemas/User"
                    }
                  }
                }
              }
            }
          }
        },
        "tags": [
          "用户管理"
        ],
        "security": [
          {
            "bearer": []
          }
        ]
      },
      "patch": {
        "operationId": "UserController_update",
        "summary": "更新用户信息",
        "parameters": [
          {
            "name": "id",
            "required": true,
            "in": "path",
            "schema": {
              "type": "string"
            }
          }
        ],
        "requestBody": {
          "required": true,
          "description": "更新的用户信息",
          "content": {
            "application/json": {
              "schema": {
                "$ref": "#/components/schemas/UpdateUserDto"
              }
            }
          }
        },
        "responses": {
          "200": {
            "description": "成功更新用户信息",
            "content": {
              "application/json": {
                "schema": {
                  "type": "object",
                  "properties": {
                    "code": {
                      "type": "number",
                      "example": 0
                    },
                    "message": {
                      "type": "string",
                      "example": "成功"
                    },
                    "data": {
                      "$ref": "#/components/schemas/User"
                    }
                  }
                }
              }
            }
          }
        },
        "tags": [
          "用户管理"
        ],
        "security": [
          {
            "bearer": []
          }
        ]
      },
      "delete": {
        "operationId": "UserController_remove",
        "summary": "删除用户",
        "parameters": [
          {
            "name": "id",
            "required": true,
            "in": "path",
            "schema": {
              "type": "string"
            }
          }
        ],
        "responses": {
          "204": {
            "description": "成功删除用户"
          }
        },
        "tags": [
          "用户管理"
        ],
        "security": [
          {
            "bearer": []
          }
        ]
      }
    },
    "/api/categories": {
      "post": {
        "operationId": "CategoryController_create",
        "summary": "创建分类",
        "parameters": [],
        "requestBody": {
          "required": true,
          "description": "分类信息",
          "content": {
            "application/json": {
              "schema": {
                "$ref": "#/components/schemas/CreateCategoryDto"
              }
            }
          }
        },
        "responses": {
          "201": {
            "description": "成功创建分类",
            "content": {
              "application/json": {
                "schema": {
                  "type": "object",
                  "properties": {
                    "code": {
                      "type": "number",
                      "example": 0
                    },
                    "message": {
                      "type": "string",
                      "example": "成功"
                    },
                    "data": {
                      "$ref": "#/components/schemas/Category"
                    }
                  }
                }
              }
            }
          }
        },
        "tags": [
          "菜品分类管理"
        ],
        "security": [
          {
            "bearer": []
          }
        ]
      },
      "get": {
        "operationId": "CategoryController_findAll",
        "summary": "获取分类列表",
        "parameters": [],
        "responses": {
          "200": {
            "description": "成功获取分类列表",
            "content": {
              "application/json": {
                "schema": {
                  "type": "object",
                  "properties": {
                    "code": {
                      "type": "number",
                      "example": 0
                    },
                    "message": {
                      "type": "string",
                      "example": "成功"
                    },
                    "data": {
                      "type": "array",
                      "items": {
                        "$ref": "#/components/schemas/Category"
                      }
                    }
                  }
                }
              }
            }
          }
        },
        "tags": [
          "菜品分类管理"
        ]
      }
    },
    "/api/categories/{id}": {
      "get": {
        "operationId": "CategoryController_findOne",
        "summary": "获取分类详情",
        "parameters": [
          {
            "name": "id",
            "required": true,
            "in": "path",
            "schema": {
              "type": "string"
            }
          }
        ],
        "responses": {
          "200": {
            "description": "成功获取分类详情",
            "content": {
              "application/json": {
                "schema": {
                  "type": "object",
                  "properties": {
                    "code": {
                      "type": "number",
                      "example": 0
                    },
                    "message": {
                      "type": "string",
                      "example": "成功"
                    },
                    "data": {
                      "$ref": "#/components/schemas/Category"
                    }
                  }
                }
              }
            }
          }
        },
        "tags": [
          "菜品分类管理"
        ],
        "security": [
          {
            "bearer": []
          }
        ]
      },
      "patch": {
        "operationId": "CategoryController_update",
        "summary": "更新分类",
        "parameters": [
          {
            "name": "id",
            "required": true,
            "in": "path",
            "schema": {
              "type": "string"
            }
          }
        ],
        "requestBody": {
          "required": true,
          "description": "更新的分类信息",
          "content": {
            "application/json": {
              "schema": {
                "$ref": "#/components/schemas/UpdateCategoryDto"
              }
            }
          }
        },
        "responses": {
          "200": {
            "description": "成功更新分类",
            "content": {
              "application/json": {
                "schema": {
                  "type": "object",
                  "properties": {
                    "code": {
                      "type": "number",
                      "example": 0
                    },
                    "message": {
                      "type": "string",
                      "example": "成功"
                    },
                    "data": {
                      "$ref": "#/components/schemas/Category"
                    }
                  }
                }
              }
            }
          }
        },
        "tags": [
          "菜品分类管理"
        ],
        "security": [
          {
            "bearer": []
          }
        ]
      },
      "delete": {
        "operationId": "CategoryController_remove",
        "summary": "删除分类",
        "parameters": [
          {
            "name": "id",
            "required": true,
            "in": "path",
            "schema": {
              "type": "string"
            }
          }
        ],
        "responses": {
          "204": {
            "description": "成功删除分类"
          }
        },
        "tags": [
          "菜品分类管理"
        ],
        "security": [
          {
            "bearer": []
          }
        ]
      }
    },
    "/api/dishes": {
      "post": {
        "operationId": "DishController_create",
        "summary": "创建菜品",
        "parameters": [],
        "requestBody": {
          "required": true,
          "description": "菜品信息",
          "content": {
            "application/json": {
              "schema": {
                "$ref": "#/components/schemas/CreateDishDto"
              }
            }
          }
        },
        "responses": {
          "201": {
            "description": "成功创建菜品",
            "content": {
              "application/json": {
                "schema": {
                  "type": "object",
                  "properties": {
                    "code": {
                      "type": "number",
                      "example": 0
                    },
                    "message": {
                      "type": "string",
                      "example": "成功"
                    },
                    "data": {
                      "$ref": "#/components/schemas/Dish"
                    }
                  }
                }
              }
            }
          }
        },
        "tags": [
          "菜品管理"
        ],
        "security": [
          {
            "bearer": []
          }
        ]
      },
      "get": {
        "operationId": "DishController_findAll",
        "summary": "获取菜品列表",
        "parameters": [
          {
            "name": "categoryId",
            "required": false,
            "in": "query",
            "description": "分类ID",
            "schema": {
              "type": "string"
            }
          }
        ],
        "responses": {
          "200": {
            "description": "成功获取菜品列表",
            "content": {
              "application/json": {
                "schema": {
                  "type": "object",
                  "properties": {
                    "code": {
                      "type": "number",
                      "example": 0
                    },
                    "message": {
                      "type": "string",
                      "example": "成功"
                    },
                    "data": {
                      "type": "array",
                      "items": {
                        "$ref": "#/components/schemas/Dish"
                      }
                    }
                  }
                }
              }
            }
          }
        },
        "tags": [
          "菜品管理"
        ]
      }
    },
    "/api/dishes/today": {
      "get": {
        "operationId": "DishController_findTodaySupply",
        "summary": "获取今日供应菜品",
        "parameters": [],
        "responses": {
          "200": {
            "description": "成功获取今日供应菜品",
            "content": {
              "application/json": {
                "schema": {
                  "type": "object",
                  "properties": {
                    "code": {
                      "type": "number",
                      "example": 0
                    },
                    "message": {
                      "type": "string",
                      "example": "成功"
                    },
                    "data": {
                      "type": "array",
                      "items": {
                        "$ref": "#/components/schemas/Dish"
                      }
                    }
                  }
                }
              }
            }
          }
        },
        "tags": [
          "菜品管理"
        ]
      }
    },
    "/api/dishes/{id}": {
      "get": {
        "operationId": "DishController_findOne",
        "summary": "获取菜品详情",
        "parameters": [
          {
            "name": "id",
            "required": true,
            "in": "path",
            "schema": {
              "type": "string"
            }
          }
        ],
        "responses": {
          "200": {
            "description": "成功获取菜品详情",
            "content": {
              "application/json": {
                "schema": {
                  "type": "object",
                  "properties": {
                    "code": {
                      "type": "number",
                      "example": 0
                    },
                    "message": {
                      "type": "string",
                      "example": "成功"
                    },
                    "data": {
                      "$ref": "#/components/schemas/Dish"
                    }
                  }
                }
              }
            }
          }
        },
        "tags": [
          "菜品管理"
        ],
        "security": [
          {
            "bearer": []
          }
        ]
      },
      "patch": {
        "operationId": "DishController_update",
        "summary": "更新菜品",
        "parameters": [
          {
            "name": "id",
            "required": true,
            "in": "path",
            "schema": {
              "type": "string"
            }
          }
        ],
        "requestBody": {
          "required": true,
          "description": "更新的菜品信息",
          "content": {
            "application/json": {
              "schema": {
                "$ref": "#/components/schemas/UpdateDishDto"
              }
            }
          }
        },
        "responses": {
          "200": {
            "description": "成功更新菜品",
            "content": {
              "application/json": {
                "schema": {
                  "type": "object",
                  "properties": {
                    "code": {
                      "type": "number",
                      "example": 0
                    },
                    "message": {
                      "type": "string",
                      "example": "成功"
                    },
                    "data": {
                      "$ref": "#/components/schemas/Dish"
                    }
                  }
                }
              }
            }
          }
        },
        "tags": [
          "菜品管理"
        ],
        "security": [
          {
            "bearer": []
          }
        ]
      },
      "delete": {
        "operationId": "DishController_remove",
        "summary": "删除菜品",
        "parameters": [
          {
            "name": "id",
            "required": true,
            "in": "path",
            "schema": {
              "type": "string"
            }
          }
        ],
        "responses": {
          "204": {
            "description": "成功删除菜品"
          }
        },
        "tags": [
          "菜品管理"
        ],
        "security": [
          {
            "bearer": []
          }
        ]
      }
    },
    "/api/dishes/{id}/sold-out": {
      "patch": {
        "operationId": "DishController_setSoldOut",
        "summary": "设置售罄状态",
        "parameters": [
          {
            "name": "id",
            "required": true,
            "in": "path",
            "schema": {
              "type": "string"
            }
          }
        ],
        "responses": {
          "200": {
            "description": "成功设置售罄状态",
            "content": {
              "application/json": {
                "schema": {
                  "type": "object",
                  "properties": {
                    "code": {
                      "type": "number",
                      "example": 0
                    },
                    "message": {
                      "type": "string",
                      "example": "成功"
                    },
                    "data": {
                      "$ref": "#/components/schemas/Dish"
                    }
                  }
                }
              }
            }
          }
        },
        "tags": [
          "菜品管理"
        ],
        "security": [
          {
            "bearer": []
          }
        ]
      }
    },
    "/api/dishes/{id}/today-supply": {
      "patch": {
        "operationId": "DishController_setTodaySupply",
        "summary": "设置今日供应状态",
        "parameters": [
          {
            "name": "id",
            "required": true,
            "in": "path",
            "schema": {
              "type": "string"
            }
          }
        ],
        "responses": {
          "200": {
            "description": "成功设置今日供应状态",
            "content": {
              "application/json": {
                "schema": {
                  "type": "object",
                  "properties": {
                    "code": {
                      "type": "number",
                      "example": 0
                    },
                    "message": {
                      "type": "string",
                      "example": "成功"
                    },
                    "data": {
                      "$ref": "#/components/schemas/Dish"
                    }
                  }
                }
              }
            }
          }
        },
        "tags": [
          "菜品管理"
        ],
        "security": [
          {
            "bearer": []
          }
        ]
      }
    },
    "/api/dishes/batch/today-supply": {
      "post": {
        "operationId": "DishController_batchSetTodaySupply",
        "summary": "批量设置今日供应",
        "parameters": [],
        "requestBody": {
          "required": true,
          "content": {
            "application/json": {
              "schema": {
                "$ref": "#/components/schemas/BatchTodaySupplyDto"
              }
            }
          }
        },
        "responses": {
          "200": {
            "description": "成功批量设置今日供应",
            "content": {
              "application/json": {
                "schema": {
                  "type": "object",
                  "properties": {
                    "code": {
                      "type": "number",
                      "example": 0
                    },
                    "message": {
                      "type": "string",
                      "example": "成功"
                    },
                    "data": {
                      "type": "object",
                      "properties": {
                        "success": {
                          "type": "boolean",
                          "example": true
                        },
                        "updatedCount": {
                          "type": "number",
                          "example": 5
                        },
                        "message": {
                          "type": "string",
                          "example": "批量操作成功"
                        }
                      }
                    }
                  }
                }
              }
            }
          },
          "201": {
            "description": "",
            "content": {
              "application/json": {
                "schema": {
                  "type": "object"
                }
              }
            }
          }
        },
        "tags": [
          "菜品管理"
        ],
        "security": [
          {
            "bearer": []
          }
        ]
      }
    },
    "/api/dishes/batch/sold-out": {
      "post": {
        "operationId": "DishController_batchSetSoldOut",
        "summary": "批量设置售罄",
        "parameters": [],
        "requestBody": {
          "required": true,
          "content": {
            "application/json": {
              "schema": {
                "$ref": "#/components/schemas/BatchSoldOutDto"
              }
            }
          }
        },
        "responses": {
          "200": {
            "description": "成功批量设置售罄",
            "content": {
              "application/json": {
                "schema": {
                  "type": "object",
                  "properties": {
                    "code": {
                      "type": "number",
                      "example": 0
                    },
                    "message": {
                      "type": "string",
                      "example": "成功"
                    },
                    "data": {
                      "type": "object",
                      "properties": {
                        "success": {
                          "type": "boolean",
                          "example": true
                        },
                        "updatedCount": {
                          "type": "number",
                          "example": 3
                        },
                        "message": {
                          "type": "string",
                          "example": "批量操作成功"
                        }
                      }
                    }
                  }
                }
              }
            }
          },
          "201": {
            "description": "",
            "content": {
              "application/json": {
                "schema": {
                  "type": "object"
                }
              }
            }
          }
        },
        "tags": [
          "菜品管理"
        ],
        "security": [
          {
            "bearer": []
          }
        ]
      }
    },
    "/api/dishes/batch/available": {
      "post": {
        "operationId": "DishController_batchSetAvailable",
        "summary": "批量设置上架状态",
        "parameters": [],
        "requestBody": {
          "required": true,
          "content": {
            "application/json": {
              "schema": {
                "$ref": "#/components/schemas/BatchAvailableDto"
              }
            }
          }
        },
        "responses": {
          "200": {
            "description": "成功批量设置上架状态",
            "content": {
              "application/json": {
                "schema": {
                  "type": "object",
                  "properties": {
                    "code": {
                      "type": "number",
                      "example": 0
                    },
                    "message": {
                      "type": "string",
                      "example": "成功"
                    },
                    "data": {
                      "type": "object",
                      "properties": {
                        "success": {
                          "type": "boolean",
                          "example": true
                        },
                        "updatedCount": {
                          "type": "number",
                          "example": 8
                        },
                        "message": {
                          "type": "string",
                          "example": "批量操作成功"
                        }
                      }
                    }
                  }
                }
              }
            }
          },
          "201": {
            "description": "",
            "content": {
              "application/json": {
                "schema": {
                  "type": "object"
                }
              }
            }
          }
        },
        "tags": [
          "菜品管理"
        ],
        "security": [
          {
            "bearer": []
          }
        ]
      }
    },
    "/api/orders": {
      "post": {
        "operationId": "OrderController_create",
        "summary": "创建订单",
        "parameters": [],
        "requestBody": {
          "required": true,
          "description": "订单信息",
          "content": {
            "application/json": {
              "schema": {
                "$ref": "#/components/schemas/CreateOrderDto"
              }
            }
          }
        },
        "responses": {
          "201": {
            "description": "",
            "content": {
              "application/json": {
                "schema": {
                  "$ref": "#/components/schemas/Order"
                }
              }
            }
          }
        },
        "tags": [
          "订单管理"
        ],
        "security": [
          {
            "bearer": []
          }
        ]
      },
      "get": {
        "operationId": "OrderController_findAll",
        "summary": "获取订单列表",
        "parameters": [
          {
            "name": "status",
            "required": false,
            "in": "query",
            "schema": {
              "enum": [
                "pending_payment",
                "paid",
                "preparing",
                "completed",
                "cancelled"
              ],
              "type": "string"
            }
          }
        ],
        "responses": {
          "200": {
            "description": "成功获取订单列表",
            "content": {
              "application/json": {
                "schema": {
                  "type": "object",
                  "properties": {
                    "items": {
                      "type": "array",
                      "items": {
                        "$ref": "#/components/schemas/Order"
                      }
                    },
                    "page": {
                      "type": "number",
                      "example": 1
                    },
                    "limit": {
                      "type": "number",
                      "example": 10
                    },
                    "total": {
                      "type": "number",
                      "example": 3
                    },
                    "totalPages": {
                      "type": "number",
                      "example": 1
                    }
                  }
                }
              }
            }
          }
        },
        "tags": [
          "订单管理"
        ],
        "security": [
          {
            "bearer": []
          }
        ]
      }
    },
    "/api/orders/{id}/pay": {
      "post": {
        "operationId": "OrderController_pay",
        "summary": "支付订单",
        "parameters": [
          {
            "name": "id",
            "required": true,
            "in": "path",
            "schema": {
              "type": "string"
            }
          }
        ],
        "responses": {
          "201": {
            "description": "",
            "content": {
              "application/json": {
                "schema": {
                  "$ref": "#/components/schemas/Order"
                }
              }
            }
          }
        },
        "tags": [
          "订单管理"
        ],
        "security": [
          {
            "bearer": []
          }
        ]
      }
    },
    "/api/orders/{id}/cancel": {
      "post": {
        "operationId": "OrderController_cancel",
        "summary": "取消订单",
        "parameters": [
          {
            "name": "id",
            "required": true,
            "in": "path",
            "schema": {
              "type": "string"
            }
          }
        ],
        "responses": {
          "201": {
            "description": "",
            "content": {
              "application/json": {
                "schema": {
                  "$ref": "#/components/schemas/Order"
                }
              }
            }
          }
        },
        "tags": [
          "订单管理"
        ],
        "security": [
          {
            "bearer": []
          }
        ]
      }
    },
    "/api/orders/filter": {
      "get": {
        "operationId": "OrderController_findByFilter",
        "summary": "智能筛选订单",
        "description": "支持多维度筛选：状态、日期范围、用户、订单号、金额范围",
        "parameters": [
          {
            "name": "status",
            "required": false,
            "in": "query",
            "description": "订单状态（多选，用逗号分隔）",
            "schema": {
              "type": "array",
              "items": {
                "type": "string",
                "enum": [
                  "pending_payment",
                  "paid",
                  "preparing",
                  "completed",
                  "cancelled"
                ]
              }
            }
          },
          {
            "name": "dateRange",
            "required": false,
            "in": "query",
            "description": "预设日期范围",
            "schema": {
              "enum": [
                "today",
                "yesterday",
                "last7days",
                "last30days",
                "custom"
              ],
              "type": "string"
            }
          },
          {
            "name": "startDate",
            "required": false,
            "in": "query",
            "description": "开始日期 (YYYY-MM-DD)",
            "schema": {
              "type": "string"
            }
          },
          {
            "name": "endDate",
            "required": false,
            "in": "query",
            "description": "结束日期 (YYYY-MM-DD)",
            "schema": {
              "type": "string"
            }
          },
          {
            "name": "userId",
            "required": false,
            "in": "query",
            "description": "用户ID筛选",
            "schema": {
              "type": "string"
            }
          },
          {
            "name": "orderNo",
            "required": false,
            "in": "query",
            "description": "订单号模糊搜索",
            "schema": {
              "type": "string"
            }
          },
          {
            "name": "minAmount",
            "required": false,
            "in": "query",
            "description": "最小金额",
            "schema": {
              "minimum": 0,
              "type": "number"
            }
          },
          {
            "name": "maxAmount",
            "required": false,
            "in": "query",
            "description": "最大金额",
            "schema": {
              "minimum": 0,
              "type": "number"
            }
          },
          {
            "name": "sortBy",
            "required": false,
            "in": "query",
            "description": "排序方式",
            "schema": {
              "default": "createdAt_desc",
              "enum": [
                "createdAt_desc",
                "createdAt_asc",
                "totalAmount_desc",
                "totalAmount_asc"
              ],
              "type": "string"
            }
          },
          {
            "name": "page",
            "required": false,
            "in": "query",
            "description": "页码",
            "schema": {
              "minimum": 1,
              "default": 1,
              "type": "number"
            }
          },
          {
            "name": "pageSize",
            "required": false,
            "in": "query",
            "description": "每页数量",
            "schema": {
              "minimum": 1,
              "default": 10,
              "type": "number"
            }
          }
        ],
        "responses": {
          "200": {
            "description": "成功获取筛选后的订单列表",
            "content": {
              "application/json": {
                "schema": {
                  "type": "object",
                  "properties": {
                    "items": {
                      "type": "array",
                      "items": {
                        "$ref": "#/components/schemas/Order"
                      }
                    },
                    "page": {
                      "type": "number",
                      "example": 1
                    },
                    "limit": {
                      "type": "number",
                      "example": 10
                    },
                    "total": {
                      "type": "number",
                      "example": 50
                    },
                    "totalPages": {
                      "type": "number",
                      "example": 5
                    }
                  }
                }
              }
            }
          }
        },
        "tags": [
          "订单管理"
        ],
        "security": [
          {
            "bearer": []
          }
        ]
      }
    },
    "/api/orders/{id}": {
      "get": {
        "operationId": "OrderController_findOne",
        "summary": "获取订单详情",
        "parameters": [
          {
            "name": "id",
            "required": true,
            "in": "path",
            "schema": {
              "type": "string"
            }
          }
        ],
        "responses": {
          "200": {
            "description": "",
            "content": {
              "application/json": {
                "schema": {
                  "$ref": "#/components/schemas/Order"
                }
              }
            }
          }
        },
        "tags": [
          "订单管理"
        ],
        "security": [
          {
            "bearer": []
          }
        ]
      },
      "patch": {
        "operationId": "OrderController_update",
        "summary": "更新订单",
        "parameters": [
          {
            "name": "id",
            "required": true,
            "in": "path",
            "schema": {
              "type": "string"
            }
          }
        ],
        "requestBody": {
          "required": true,
          "description": "更新的订单信息",
          "content": {
            "application/json": {
              "schema": {
                "$ref": "#/components/schemas/UpdateOrderDto"
              }
            }
          }
        },
        "responses": {
          "200": {
            "description": "",
            "content": {
              "application/json": {
                "schema": {
                  "$ref": "#/components/schemas/Order"
                }
              }
            }
          }
        },
        "tags": [
          "订单管理"
        ],
        "security": [
          {
            "bearer": []
          }
        ]
      }
    },
    "/api/orders/{id}/status": {
      "patch": {
        "operationId": "OrderController_updateStatus",
        "summary": "更新订单状态",
        "parameters": [
          {
            "name": "id",
            "required": true,
            "in": "path",
            "schema": {
              "type": "string"
            }
          }
        ],
        "requestBody": {
          "required": true,
          "description": "订单状态",
          "content": {
            "application/json": {
              "schema": {
                "$ref": "#/components/schemas/UpdateOrderStatusDto"
              }
            }
          }
        },
        "responses": {
          "200": {
            "description": "",
            "content": {
              "application/json": {
                "schema": {
                  "$ref": "#/components/schemas/Order"
                }
              }
            }
          }
        },
        "tags": [
          "订单管理"
        ],
        "security": [
          {
            "bearer": []
          }
        ]
      }
    },
    "/api/statistics/dashboard": {
      "get": {
        "operationId": "StatisticsController_getDashboardOverview",
        "summary": "获取今日概览数据",
        "description": "获取今日经营概览数据，包括订单数、营收、待处理订单等",
        "parameters": [
          {
            "name": "date",
            "required": false,
            "in": "query",
            "description": "查询日期 (YYYY-MM-DD)，默认今天",
            "schema": {
              "example": "2026-03-26",
              "type": "string"
            }
          }
        ],
        "responses": {
          "200": {
            "description": "成功获取今日概览数据",
            "content": {
              "application/json": {
                "schema": {
                  "$ref": "#/components/schemas/DashboardOverviewDto"
                }
              }
            }
          }
        },
        "tags": [
          "统计 - Statistics"
        ],
        "security": [
          {
            "bearer": []
          }
        ]
      }
    },
    "/api/statistics/trends": {
      "get": {
        "operationId": "StatisticsController_getTrendData",
        "summary": "获取趋势数据",
        "description": "获取订单和营收趋势数据",
        "parameters": [
          {
            "name": "range",
            "required": false,
            "in": "query",
            "description": "时间范围：7d=近7天, 30d=近30天, custom=自定义",
            "schema": {
              "default": "7d",
              "example": "7d",
              "type": "string"
            }
          },
          {
            "name": "startDate",
            "required": false,
            "in": "query",
            "description": "开始日期 (YYYY-MM-DD)，自定义范围时使用",
            "schema": {
              "example": "2026-03-01",
              "type": "string"
            }
          },
          {
            "name": "endDate",
            "required": false,
            "in": "query",
            "description": "结束日期 (YYYY-MM-DD)，自定义范围时使用",
            "schema": {
              "example": "2026-03-26",
              "type": "string"
            }
          },
          {
            "name": "type",
            "required": false,
            "in": "query",
            "description": "趋势类型：order=订单, revenue=营收, both=两者",
            "schema": {
              "default": "both",
              "example": "both",
              "enum": [
                "order",
                "revenue",
                "both"
              ],
              "type": "string"
            }
          }
        ],
        "responses": {
          "200": {
            "description": "成功获取趋势数据",
            "content": {
              "application/json": {
                "schema": {
                  "$ref": "#/components/schemas/TrendResponseDto"
                }
              }
            }
          }
        },
        "tags": [
          "统计 - Statistics"
        ],
        "security": [
          {
            "bearer": []
          }
        ]
      }
    },
    "/api/statistics/hourly-distribution": {
      "get": {
        "operationId": "StatisticsController_getHourlyDistribution",
        "summary": "获取时段分布",
        "description": "获取近7天的订单时段分布数据",
        "parameters": [],
        "responses": {
          "200": {
            "description": "成功获取时段分布数据",
            "content": {
              "application/json": {
                "schema": {
                  "$ref": "#/components/schemas/HourlyDistributionDto"
                }
              }
            }
          }
        },
        "tags": [
          "统计 - Statistics"
        ],
        "security": [
          {
            "bearer": []
          }
        ]
      }
    },
    "/api/statistics/dishes/ranking": {
      "get": {
        "operationId": "StatisticsController_getDishRanking",
        "summary": "获取菜品销售排行",
        "description": "获取菜品销售排行数据，支持多种排行类型",
        "parameters": [
          {
            "name": "type",
            "required": false,
            "in": "query",
            "description": "排行类型：sales=热销榜, revenue=营收榜, popularity=人气榜, unsold=滞销榜",
            "schema": {
              "default": "sales",
              "example": "sales",
              "enum": [
                "sales",
                "revenue",
                "popularity",
                "unsold"
              ],
              "type": "string"
            }
          },
          {
            "name": "range",
            "required": false,
            "in": "query",
            "description": "时间范围：7d=近7天, 30d=近30天, 90d=近90天",
            "schema": {
              "default": "30d",
              "example": "30d",
              "enum": [
                "7d",
                "30d",
                "90d"
              ],
              "type": "string"
            }
          },
          {
            "name": "categoryId",
            "required": false,
            "in": "query",
            "description": "分类ID筛选",
            "schema": {
              "example": "550e8400-e29b-41d4-a716-446655440000",
              "type": "string"
            }
          },
          {
            "name": "limit",
            "required": false,
            "in": "query",
            "description": "返回数量",
            "schema": {
              "minimum": 1,
              "default": 10,
              "example": 10,
              "type": "number"
            }
          }
        ],
        "responses": {
          "200": {
            "description": "成功获取菜品排行数据",
            "content": {
              "application/json": {
                "schema": {
                  "type": "array",
                  "items": {
                    "$ref": "#/components/schemas/DishRankingItemDto"
                  }
                }
              }
            }
          }
        },
        "tags": [
          "统计 - Statistics"
        ],
        "security": [
          {
            "bearer": []
          }
        ]
      }
    },
    "/api/statistics/users/ranking": {
      "get": {
        "operationId": "StatisticsController_getUserRanking",
        "summary": "获取用户消费排行",
        "description": "获取用户消费排行数据",
        "parameters": [
          {
            "name": "range",
            "required": false,
            "in": "query",
            "description": "时间范围：7d=近7天, 30d=近30天, 90d=近90天",
            "schema": {
              "default": "30d",
              "example": "30d",
              "enum": [
                "7d",
                "30d",
                "90d"
              ],
              "type": "string"
            }
          },
          {
            "name": "page",
            "required": false,
            "in": "query",
            "description": "页码",
            "schema": {
              "default": 1,
              "example": 1,
              "type": "number"
            }
          },
          {
            "name": "pageSize",
            "required": false,
            "in": "query",
            "description": "每页数量",
            "schema": {
              "default": 20,
              "example": 20,
              "type": "number"
            }
          },
          {
            "name": "keyword",
            "required": false,
            "in": "query",
            "description": "搜索关键词（用户昵称）",
            "schema": {
              "example": "张三",
              "type": "string"
            }
          }
        ],
        "responses": {
          "200": {
            "description": "成功获取用户排行数据",
            "content": {
              "application/json": {
                "schema": {
                  "type": "object",
                  "properties": {
                    "code": {
                      "type": "number",
                      "example": 0
                    },
                    "message": {
                      "type": "string",
                      "example": "success"
                    },
                    "data": {
                      "type": "array",
                      "items": {
                        "$ref": "#/components/schemas/UserRankingItemDto"
                      }
                    },
                    "pagination": {
                      "type": "object",
                      "properties": {
                        "page": {
                          "type": "number",
                          "example": 1
                        },
                        "pageSize": {
                          "type": "number",
                          "example": 20
                        },
                        "total": {
                          "type": "number",
                          "example": 120
                        }
                      }
                    }
                  }
                }
              }
            }
          }
        },
        "tags": [
          "统计 - Statistics"
        ],
        "security": [
          {
            "bearer": []
          }
        ]
      }
    },
    "/api/statistics/users/{id}": {
      "get": {
        "operationId": "StatisticsController_getUserStatisticsById",
        "summary": "获取用户统计",
        "description": "获取指定用户的统计信息",
        "parameters": [
          {
            "name": "id",
            "required": true,
            "in": "path",
            "description": "用户ID",
            "schema": {
              "example": "550e8400-e29b-41d4-a716-446655440002",
              "type": "string"
            }
          }
        ],
        "responses": {
          "200": {
            "description": "成功获取用户统计信息",
            "content": {
              "application/json": {
                "schema": {
                  "$ref": "#/components/schemas/UserStatisticsDto"
                }
              }
            }
          }
        },
        "tags": [
          "统计 - Statistics"
        ],
        "security": [
          {
            "bearer": []
          }
        ]
      }
    },
    "/api/statistics/my": {
      "get": {
        "operationId": "StatisticsController_getMyStatistics",
        "summary": "获取我的统计",
        "description": "获取当前登录用户的个人统计信息",
        "parameters": [],
        "responses": {
          "200": {
            "description": "成功获取当前用户统计信息",
            "content": {
              "application/json": {
                "schema": {
                  "$ref": "#/components/schemas/UserStatisticsDto"
                }
              }
            }
          }
        },
        "tags": [
          "统计 - Statistics"
        ],
        "security": [
          {
            "bearer": []
          }
        ]
      }
    }
  },
  "info": {
    "title": "Food Service API",
    "description": "餐饮服务后端 API 文档",
    "version": "1.0",
    "contact": {}
  },
  "tags": [],
  "servers": [],
  "components": {
    "securitySchemes": {
      "bearer": {
        "scheme": "bearer",
        "bearerFormat": "JWT",
        "type": "http"
      }
    },
    "schemas": {
      "AuthResponseDto": {
        "type": "object",
        "properties": {
          "accessToken": {
            "type": "string",
            "description": "访问令牌",
            "example": "eyJhbGciOiJIUzI1NiIsInR5cCI6IkpXVCJ9..."
          },
          "expiresIn": {
            "type": "number",
            "description": "过期时间（秒）",
            "example": 3600
          },
          "user": {
            "type": "object",
            "description": "用户信息",
            "example": {
              "id": "uuid",
              "username": "john_doe",
              "role": "user"
            }
          }
        },
        "required": [
          "accessToken",
          "expiresIn",
          "user"
        ]
      },
      "RegisterDto": {
        "type": "object",
        "properties": {
          "username": {
            "type": "string",
            "minLength": 3,
            "maxLength": 32,
            "description": "用户名",
            "example": "john_doe"
          },
          "nickname": {
            "type": "string",
            "description": "昵称",
            "example": "John Doe"
          },
          "phone": {
            "type": "string",
            "description": "手机号",
            "example": "13800138000"
          },
          "email": {
            "type": "string",
            "description": "邮箱",
            "example": "user@example.com"
          },
          "password": {
            "type": "string",
            "minLength": 6,
            "maxLength": 32,
            "description": "密码",
            "example": "password123"
          },
          "avatar": {
            "type": "string",
            "description": "头像 URL",
            "example": "https://example.com/avatar.jpg"
          }
        },
        "required": [
          "password"
        ]
      },
      "LoginDto": {
        "type": "object",
        "properties": {
          "username": {
            "type": "string",
            "description": "用户名",
            "example": "john_doe"
          },
          "email": {
            "type": "string",
            "description": "邮箱",
            "example": "user@example.com"
          },
          "phone": {
            "type": "string",
            "description": "手机号（中国大陆）",
            "example": "13800138000"
          },
          "password": {
            "type": "string",
            "description": "密码",
            "example": "password123"
          }
        },
        "required": [
          "password"
        ]
      },
      "WechatLoginDto": {
        "type": "object",
        "properties": {
          "code": {
            "type": "string",
            "description": "微信授权码",
            "example": "xxxxxxxxxxxxxxxx"
          }
        },
        "required": [
          "code"
        ]
      },
      "User": {
        "type": "object",
        "properties": {
          "id": {
            "type": "string",
            "description": "用户 ID",
            "example": "550e8400-e29b-41d4-a716-446655440000"
          },
          "username": {
            "type": "string",
            "description": "用户名",
            "example": "john_doe"
          },
          "nickname": {
            "type": "string",
            "description": "昵称",
            "example": "John Doe"
          },
          "phone": {
            "type": "string",
            "description": "手机号",
            "example": "13800138000"
          },
          "email": {
            "type": "string",
            "description": "邮箱",
            "example": "user@example.com"
          },
          "openId": {
            "type": "string",
            "description": "微信 openId",
            "example": "oabcdef123456"
          },
          "unionId": {
            "type": "string",
            "description": "微信 unionId",
            "example": "ouabcdef123456"
          },
          "avatar": {
            "type": "string",
            "description": "头像 URL",
            "example": "https://example.com/avatar.jpg"
          },
          "role": {
            "enum": [
              "admin",
              "merchant",
              "user"
            ],
            "type": "string",
            "description": "用户角色",
            "example": "user"
          },
          "status": {
            "enum": [
              "active",
              "inactive",
              "banned"
            ],
            "type": "string",
            "description": "用户状态",
            "example": "active"
          },
          "createdAt": {
            "format": "date-time",
            "type": "string",
            "description": "创建时间",
            "example": "2024-01-01T00:00:00.000Z"
          },
          "updatedAt": {
            "format": "date-time",
            "type": "string",
            "description": "更新时间",
            "example": "2024-01-01T00:00:00.000Z"
          },
          "password": {
            "type": "string"
          }
        },
        "required": [
          "id",
          "role",
          "status",
          "createdAt",
          "updatedAt",
          "password"
        ]
      },
      "CreateUserDto": {
        "type": "object",
        "properties": {
          "username": {
            "type": "string",
            "minLength": 3,
            "maxLength": 32,
            "description": "用户名",
            "example": "john_doe"
          },
          "nickname": {
            "type": "string",
            "description": "昵称",
            "example": "John Doe"
          },
          "phone": {
            "type": "string",
            "description": "手机号",
            "example": "13800138000"
          },
          "email": {
            "type": "string",
            "description": "邮箱",
            "example": "user@example.com"
          },
          "password": {
            "type": "string",
            "minLength": 6,
            "maxLength": 32,
            "description": "密码",
            "example": "password123"
          },
          "avatar": {
            "type": "string",
            "description": "头像 URL",
            "example": "https://example.com/avatar.jpg"
          },
          "role": {
            "enum": [
              "admin",
              "merchant",
              "user"
            ],
            "type": "string",
            "description": "用户角色",
            "example": "user"
          }
        },
        "required": [
          "password"
        ]
      },
      "UpdateUserDto": {
        "type": "object",
        "properties": {
          "username": {
            "type": "string",
            "minLength": 3,
            "maxLength": 32,
            "description": "用户名",
            "example": "john_doe"
          },
          "nickname": {
            "type": "string",
            "description": "昵称",
            "example": "John Doe"
          },
          "phone": {
            "type": "string",
            "description": "手机号",
            "example": "13800138000"
          },
          "email": {
            "type": "string",
            "description": "邮箱",
            "example": "user@example.com"
          },
          "password": {
            "type": "string",
            "minLength": 6,
            "maxLength": 32,
            "description": "密码",
            "example": "password123"
          },
          "avatar": {
            "type": "string",
            "description": "头像 URL",
            "example": "https://example.com/avatar.jpg"
          },
          "role": {
            "enum": [
              "admin",
              "merchant",
              "user"
            ],
            "type": "string",
            "description": "用户角色",
            "example": "user"
          }
        }
      },
      "Category": {
        "type": "object",
        "properties": {
          "id": {
            "type": "string",
            "description": "分类 ID",
            "example": "550e8400-e29b-41d4-a716-446655440000"
          },
          "name": {
            "type": "string",
            "description": "分类名称",
            "example": "热菜"
          },
          "sortOrder": {
            "type": "number",
            "description": "排序值",
            "example": 1
          },
          "enabled": {
            "type": "boolean",
            "description": "是否启用",
            "example": true
          },
          "dishes": {
            "description": "关联的菜品列表",
            "type": "array",
            "items": {
              "$ref": "#/components/schemas/Dish"
            }
          },
          "createdAt": {
            "format": "date-time",
            "type": "string",
            "description": "创建时间",
            "example": "2024-01-01T00:00:00.000Z"
          },
          "updatedAt": {
            "format": "date-time",
            "type": "string",
            "description": "更新时间",
            "example": "2024-01-01T00:00:00.000Z"
          }
        },
        "required": [
          "id",
          "name",
          "sortOrder",
          "enabled",
          "createdAt",
          "updatedAt"
        ]
      },
      "Dish": {
        "type": "object",
        "properties": {
          "id": {
            "type": "string",
            "description": "菜品 ID",
            "example": "550e8400-e29b-41d4-a716-446655440000"
          },
          "categoryId": {
            "type": "string",
            "description": "分类 ID",
            "example": "550e8400-e29b-41d4-a716-446655440000"
          },
          "category": {
            "description": "关联的分类",
            "allOf": [
              {
                "$ref": "#/components/schemas/Category"
              }
            ]
          },
          "name": {
            "type": "string",
            "description": "菜品名称",
            "example": "宫保鸡丁"
          },
          "price": {
            "type": "number",
            "description": "价格",
            "example": 28.8
          },
          "image": {
            "type": "string",
            "description": "图片 URL",
            "example": "https://example.com/dish.jpg"
          },
          "description": {
            "type": "string",
            "description": "描述",
            "example": "经典川菜，口味麻辣鲜香"
          },
          "available": {
            "type": "boolean",
            "description": "是否在售",
            "example": true
          },
          "todaySupply": {
            "type": "boolean",
            "description": "今日是否供应",
            "example": true
          },
          "soldOut": {
            "type": "boolean",
            "description": "是否售罄",
            "example": false
          },
          "sortOrder": {
            "type": "number",
            "description": "排序值",
            "example": 1
          },
          "deletedAt": {
            "format": "date-time",
            "type": "string",
            "description": "删除时间",
            "example": "2024-01-01T00:00:00.000Z"
          },
          "createdAt": {
            "format": "date-time",
            "type": "string",
            "description": "创建时间",
            "example": "2024-01-01T00:00:00.000Z"
          },
          "updatedAt": {
            "format": "date-time",
            "type": "string",
            "description": "更新时间",
            "example": "2024-01-01T00:00:00.000Z"
          }
        },
        "required": [
          "id",
          "categoryId",
          "name",
          "price",
          "available",
          "todaySupply",
          "soldOut",
          "sortOrder",
          "createdAt",
          "updatedAt"
        ]
      },
      "CreateCategoryDto": {
        "type": "object",
        "properties": {
          "name": {
            "type": "string",
            "description": "分类名称",
            "example": "热菜"
          },
          "sortOrder": {
            "type": "number",
            "minimum": 0,
            "description": "排序值",
            "example": 1
          }
        },
        "required": [
          "name"
        ]
      },
      "UpdateCategoryDto": {
        "type": "object",
        "properties": {
          "name": {
            "type": "string",
            "description": "分类名称",
            "example": "热菜"
          },
          "sortOrder": {
            "type": "number",
            "minimum": 0,
            "description": "排序值",
            "example": 1
          }
        }
      },
      "CreateDishDto": {
        "type": "object",
        "properties": {
          "categoryId": {
            "type": "string",
            "description": "分类ID",
            "example": "550e8400-e29b-41d4-a716-446655440001"
          },
          "name": {
            "type": "string",
            "description": "菜品名称",
            "example": "宫保鸡丁"
          },
          "price": {
            "type": "number",
            "minimum": 0,
            "description": "价格",
            "example": 38.8
          },
          "image": {
            "type": "string",
            "description": "图片URL",
            "example": "https://example.com/dish.jpg"
          },
          "description": {
            "type": "string",
            "description": "描述",
            "example": "经典川菜，麻辣鲜香"
          },
          "available": {
            "type": "boolean",
            "description": "是否在售",
            "example": true
          },
          "todaySupply": {
            "type": "boolean",
            "description": "今日是否供应",
            "example": true
          },
          "sortOrder": {
            "type": "number",
            "minimum": 0,
            "description": "排序值",
            "example": 1
          }
        },
        "required": [
          "categoryId",
          "name",
          "price"
        ]
      },
      "UpdateDishDto": {
        "type": "object",
        "properties": {
          "categoryId": {
            "type": "string",
            "description": "分类ID",
            "example": "550e8400-e29b-41d4-a716-446655440001"
          },
          "name": {
            "type": "string",
            "description": "菜品名称",
            "example": "宫保鸡丁"
          },
          "price": {
            "type": "number",
            "minimum": 0,
            "description": "价格",
            "example": 38.8
          },
          "image": {
            "type": "string",
            "description": "图片URL",
            "example": "https://example.com/dish.jpg"
          },
          "description": {
            "type": "string",
            "description": "描述",
            "example": "经典川菜，麻辣鲜香"
          },
          "available": {
            "type": "boolean",
            "description": "是否在售",
            "example": true
          },
          "todaySupply": {
            "type": "boolean",
            "description": "今日是否供应",
            "example": true
          },
          "sortOrder": {
            "type": "number",
            "minimum": 0,
            "description": "排序值",
            "example": 1
          }
        }
      },
      "BatchTodaySupplyDto": {
        "type": "object",
        "properties": {
          "dishIds": {
            "description": "菜品ID数组",
            "example": [
              "uuid1",
              "uuid2"
            ],
            "type": "array",
            "items": {
              "type": "string"
            }
          },
          "todaySupply": {
            "type": "boolean",
            "description": "是否今日供应",
            "example": true
          }
        },
        "required": [
          "dishIds",
          "todaySupply"
        ]
      },
      "BatchSoldOutDto": {
        "type": "object",
        "properties": {
          "dishIds": {
            "description": "菜品ID数组",
            "example": [
              "uuid1",
              "uuid2"
            ],
            "type": "array",
            "items": {
              "type": "string"
            }
          },
          "soldOut": {
            "type": "boolean",
            "description": "是否售罄",
            "example": true
          }
        },
        "required": [
          "dishIds",
          "soldOut"
        ]
      },
      "BatchAvailableDto": {
        "type": "object",
        "properties": {
          "dishIds": {
            "description": "菜品ID数组",
            "example": [
              "uuid1",
              "uuid2"
            ],
            "type": "array",
            "items": {
              "type": "string"
            }
          },
          "available": {
            "type": "boolean",
            "description": "是否上架",
            "example": true
          }
        },
        "required": [
          "dishIds",
          "available"
        ]
      },
      "Order": {
        "type": "object",
        "properties": {
          "id": {
            "type": "string",
            "description": "订单 ID",
            "example": "550e8400-e29b-41d4-a716-446655440000"
          },
          "orderNo": {
            "type": "string",
            "description": "订单号",
            "example": "ORD202401010001"
          },
          "userId": {
            "type": "string",
            "description": "用户 ID",
            "example": "550e8400-e29b-41d4-a716-446655440000"
          },
          "user": {
            "description": "关联的用户",
            "allOf": [
              {
                "$ref": "#/components/schemas/User"
              }
            ]
          },
          "items": {
            "description": "订单明细",
            "type": "array",
            "items": {
              "$ref": "#/components/schemas/OrderItem"
            }
          },
          "totalAmount": {
            "type": "number",
            "description": "订单总金额",
            "example": 88.8
          },
          "status": {
            "enum": [
              "pending_payment",
              "paid",
              "preparing",
              "completed",
              "cancelled"
            ],
            "type": "string",
            "description": "订单状态",
            "example": "pending_payment"
          },
          "remark": {
            "type": "string",
            "description": "备注",
            "example": "少辣，多放葱"
          },
          "paidAt": {
            "format": "date-time",
            "type": "string",
            "description": "支付时间",
            "example": "2024-01-01T00:00:00.000Z"
          },
          "completedAt": {
            "format": "date-time",
            "type": "string",
            "description": "完成时间",
            "example": "2024-01-01T00:30:00.000Z"
          },
          "createdAt": {
            "format": "date-time",
            "type": "string",
            "description": "创建时间",
            "example": "2024-01-01T00:00:00.000Z"
          },
          "updatedAt": {
            "format": "date-time",
            "type": "string",
            "description": "更新时间",
            "example": "2024-01-01T00:00:00.000Z"
          }
        },
        "required": [
          "id",
          "orderNo",
          "userId",
          "totalAmount",
          "status",
          "createdAt",
          "updatedAt"
        ]
      },
      "OrderItem": {
        "type": "object",
        "properties": {
          "id": {
            "type": "string",
            "description": "订单项 ID",
            "example": "550e8400-e29b-41d4-a716-446655440000"
          },
          "orderId": {
            "type": "string",
            "description": "订单 ID",
            "example": "550e8400-e29b-41d4-a716-446655440000"
          },
          "order": {
            "description": "关联的订单",
            "allOf": [
              {
                "$ref": "#/components/schemas/Order"
              }
            ]
          },
          "dishId": {
            "type": "string",
            "description": "菜品 ID",
            "example": "550e8400-e29b-41d4-a716-446655440000"
          },
          "dish": {
            "description": "关联的菜品",
            "allOf": [
              {
                "$ref": "#/components/schemas/Dish"
              }
            ]
          },
          "dishName": {
            "type": "string",
            "description": "菜品名称",
            "example": "宫保鸡丁"
          },
          "price": {
            "type": "number",
            "description": "单价",
            "example": 28.8
          },
          "quantity": {
            "type": "number",
            "description": "数量",
            "example": 2
          },
          "subtotal": {
            "type": "number",
            "description": "小计",
            "example": 57.6
          },
          "remark": {
            "type": "string",
            "description": "备注",
            "example": "少辣"
          }
        },
        "required": [
          "id",
          "orderId",
          "dishId",
          "dishName",
          "price",
          "quantity",
          "subtotal"
        ]
      },
      "CreateOrderItemDto": {
        "type": "object",
        "properties": {
          "dishId": {
            "type": "string",
            "description": "菜品ID",
            "example": "550e8400-e29b-41d4-a716-446655440000"
          },
          "quantity": {
            "type": "number",
            "minimum": 1,
            "description": "数量",
            "example": 2
          },
          "remark": {
            "type": "string",
            "description": "备注",
            "example": "少放辣"
          }
        },
        "required": [
          "dishId",
          "quantity"
        ]
      },
      "CreateOrderDto": {
        "type": "object",
        "properties": {
          "items": {
            "description": "订单项",
            "example": [
              {
                "dishId": "550e8400-e29b-41d4-a716-446655440000",
                "quantity": 2
              }
            ],
            "type": "array",
            "items": {
              "$ref": "#/components/schemas/CreateOrderItemDto"
            }
          },
          "remark": {
            "type": "string",
            "description": "备注",
            "example": "请尽快送达"
          }
        },
        "required": [
          "items"
        ]
      },
      "UpdateOrderStatusDto": {
        "type": "object",
        "properties": {
          "status": {
            "enum": [
              "pending_payment",
              "paid",
              "preparing",
              "completed",
              "cancelled"
            ],
            "type": "string",
            "description": "订单状态",
            "example": "paid"
          }
        },
        "required": [
          "status"
        ]
      },
      "UpdateOrderDto": {
        "type": "object",
        "properties": {
          "items": {
            "description": "订单项",
            "example": [
              {
                "dishId": "550e8400-e29b-41d4-a716-446655440000",
                "quantity": 2
              }
            ],
            "type": "array",
            "items": {
              "$ref": "#/components/schemas/CreateOrderItemDto"
            }
          },
          "remark": {
            "type": "string",
            "description": "备注",
            "example": "请尽快送达"
          },
          "status": {
            "enum": [
              "pending_payment",
              "paid",
              "preparing",
              "completed",
              "cancelled"
            ],
            "type": "string",
            "description": "订单状态"
          }
        }
      },
      "DashboardDataDto": {
        "type": "object",
        "properties": {
          "totalOrders": {
            "type": "number",
            "description": "今日订单总数",
            "example": 156
          },
          "totalRevenue": {
            "type": "number",
            "description": "今日营收总额",
            "example": 5280.5
          },
          "pendingOrders": {
            "type": "number",
            "description": "待处理订单数",
            "example": 12
          },
          "completedOrders": {
            "type": "number",
            "description": "已完成订单数",
            "example": 138
          },
          "cancelledOrders": {
            "type": "number",
            "description": "已取消订单数",
            "example": 6
          },
          "avgOrderValue": {
            "type": "number",
            "description": "平均客单价",
            "example": 33.85
          },
          "cancelRate": {
            "type": "number",
            "description": "取消率",
            "example": 3.85
          }
        },
        "required": [
          "totalOrders",
          "totalRevenue",
          "pendingOrders",
          "completedOrders",
          "cancelledOrders",
          "avgOrderValue",
          "cancelRate"
        ]
      },
      "ComparisonDataDto": {
        "type": "object",
        "properties": {
          "orderGrowth": {
            "type": "number",
            "description": "订单增长率",
            "example": 12.5
          },
          "revenueGrowth": {
            "type": "number",
            "description": "营收增长率",
            "example": 8.3
          },
          "cancelRateChange": {
            "type": "number",
            "description": "取消率变化",
            "example": -1.2
          }
        },
        "required": [
          "orderGrowth",
          "revenueGrowth",
          "cancelRateChange"
        ]
      },
      "DashboardOverviewDto": {
        "type": "object",
        "properties": {
          "today": {
            "description": "今日数据",
            "allOf": [
              {
                "$ref": "#/components/schemas/DashboardDataDto"
              }
            ]
          },
          "comparison": {
            "description": "环比数据",
            "allOf": [
              {
                "$ref": "#/components/schemas/ComparisonDataDto"
              }
            ]
          }
        },
        "required": [
          "today",
          "comparison"
        ]
      },
      "TrendDataDto": {
        "type": "object",
        "properties": {
          "dates": {
            "description": "日期数组",
            "example": [
              "2026-03-20",
              "2026-03-21",
              "2026-03-22",
              "2026-03-23",
              "2026-03-24",
              "2026-03-25",
              "2026-03-26"
            ],
            "type": "array",
            "items": {
              "type": "string"
            }
          },
          "orderCounts": {
            "description": "订单数数组",
            "example": [
              120,
              135,
              128,
              142,
              156,
              148,
              156
            ],
            "type": "array",
            "items": {
              "type": "number"
            }
          },
          "revenues": {
            "description": "营收数组",
            "example": [
              4200.5,
              4850,
              4620.3,
              5100.8,
              5280.5,
              4950.2,
              5280.5
            ],
            "type": "array",
            "items": {
              "type": "number"
            }
          }
        },
        "required": [
          "dates",
          "orderCounts",
          "revenues"
        ]
      },
      "TrendSummaryDto": {
        "type": "object",
        "properties": {
          "totalOrders": {
            "type": "number",
            "description": "总订单数",
            "example": 985
          },
          "totalRevenue": {
            "type": "number",
            "description": "总营收",
            "example": 34252.8
          },
          "avgDailyOrders": {
            "type": "number",
            "description": "日均订单数",
            "example": 140.7
          },
          "avgDailyRevenue": {
            "type": "number",
            "description": "日均营收",
            "example": 4893.26
          }
        },
        "required": [
          "totalOrders",
          "totalRevenue",
          "avgDailyOrders",
          "avgDailyRevenue"
        ]
      },
      "TrendResponseDto": {
        "type": "object",
        "properties": {
          "trend": {
            "description": "趋势数据",
            "allOf": [
              {
                "$ref": "#/components/schemas/TrendDataDto"
              }
            ]
          },
          "summary": {
            "description": "汇总数据",
            "allOf": [
              {
                "$ref": "#/components/schemas/TrendSummaryDto"
              }
            ]
          }
        },
        "required": [
          "trend",
          "summary"
        ]
      },
      "HourlyDistributionDto": {
        "type": "object",
        "properties": {
          "hours": {
            "description": "时段数组",
            "example": [
              "08:00",
              "09:00",
              "10:00",
              "11:00",
              "12:00",
              "13:00",
              "14:00",
              "15:00",
              "16:00",
              "17:00",
              "18:00",
              "19:00",
              "20:00",
              "21:00"
            ],
            "type": "array",
            "items": {
              "type": "string"
            }
          },
          "orderCounts": {
            "description": "各时段订单数",
            "example": [
              5,
              8,
              12,
              25,
              45,
              38,
              28,
              22,
              18,
              15,
              20,
              35,
              42,
              38
            ],
            "type": "array",
            "items": {
              "type": "number"
            }
          },
          "peakHour": {
            "type": "string",
            "description": "高峰时段",
            "example": "12:00"
          }
        },
        "required": [
          "hours",
          "orderCounts",
          "peakHour"
        ]
      },
      "DishRankingItemDto": {
        "type": "object",
        "properties": {
          "rank": {
            "type": "number",
            "description": "排名",
            "example": 1
          },
          "dishId": {
            "type": "string",
            "description": "菜品ID",
            "example": "550e8400-e29b-41d4-a716-446655440001"
          },
          "dishName": {
            "type": "string",
            "description": "菜品名称",
            "example": "宫保鸡丁"
          },
          "categoryName": {
            "type": "string",
            "description": "分类名称",
            "example": "川菜"
          },
          "salesCount": {
            "type": "number",
            "description": "销售数量",
            "example": 256
          },
          "salesRevenue": {
            "type": "number",
            "description": "销售额",
            "example": 6400
          },
          "orderCount": {
            "type": "number",
            "description": "被点单次数",
            "example": 180
          },
          "avgPrice": {
            "type": "number",
            "description": "平均单价",
            "example": 25
          },
          "trend": {
            "type": "string",
            "description": "趋势：上升/下降/稳定",
            "example": "up",
            "enum": [
              "up",
              "down",
              "stable"
            ]
          },
          "growthRate": {
            "type": "number",
            "description": "增长率",
            "example": 15.5
          }
        },
        "required": [
          "rank",
          "dishId",
          "dishName",
          "categoryName",
          "salesCount",
          "salesRevenue",
          "orderCount",
          "avgPrice",
          "trend",
          "growthRate"
        ]
      },
      "UserRankingItemDto": {
        "type": "object",
        "properties": {
          "rank": {
            "type": "number",
            "description": "排名",
            "example": 1
          },
          "userId": {
            "type": "string",
            "description": "用户ID",
            "example": "550e8400-e29b-41d4-a716-446655440002"
          },
          "nickname": {
            "type": "string",
            "description": "用户昵称",
            "example": "美食达人"
          },
          "avatar": {
            "type": "string",
            "description": "用户头像",
            "example": "https://example.com/avatar.jpg"
          },
          "totalSpent": {
            "type": "number",
            "description": "累计消费",
            "example": 3580.5
          },
          "orderCount": {
            "type": "number",
            "description": "订单次数",
            "example": 86
          },
          "avgOrderValue": {
            "type": "number",
            "description": "平均客单价",
            "example": 41.63
          },
          "favoriteDish": {
            "type": "string",
            "description": "最常点菜品",
            "example": "麻婆豆腐"
          },
          "lastOrderAt": {
            "format": "date-time",
            "type": "string",
            "description": "最近消费时间",
            "example": "2026-03-25T18:30:00Z"
          }
        },
        "required": [
          "rank",
          "userId",
          "nickname",
          "avatar",
          "totalSpent",
          "orderCount",
          "avgOrderValue",
          "favoriteDish",
          "lastOrderAt"
        ]
      },
      "UserFavoriteDishDto": {
        "type": "object",
        "properties": {
          "name": {
            "type": "string",
            "description": "菜品名称",
            "example": "宫保鸡丁"
          },
          "count": {
            "type": "number",
            "description": "点单次数",
            "example": 15
          }
        },
        "required": [
          "name",
          "count"
        ]
      },
      "UserStatisticsDto": {
        "type": "object",
        "properties": {
          "totalSpent": {
            "type": "number",
            "description": "累计消费",
            "example": 3580.5
          },
          "totalOrders": {
            "type": "number",
            "description": "累计订单数",
            "example": 86
          },
          "monthlySpent": {
            "type": "number",
            "description": "本月消费",
            "example": 520
          },
          "monthlyOrders": {
            "type": "number",
            "description": "本月订单数",
            "example": 12
          },
          "monthlyGrowth": {
            "type": "number",
            "description": "较上月增长率",
            "example": 8.5
          },
          "favoriteDish": {
            "description": "最爱菜品",
            "allOf": [
              {
                "$ref": "#/components/schemas/UserFavoriteDishDto"
              }
            ]
          }
        },
        "required": [
          "totalSpent",
          "totalOrders",
          "monthlySpent",
          "monthlyOrders",
          "monthlyGrowth",
          "favoriteDish"
        ]
      }
    }
  }
}
